nrndiff/__init__.py
nrndiff/_cli.py
nrndiff/_differences.py
nrndiff/_differs.py
nrndiff/_patches.py
nrndiff/_util.py
nrn_diff-0.0.3.dist-info/WHEEL
nrn_diff-0.0.3.dist-info/METADATA
nrn_diff-0.0.3.dist-info/RECORD
